b_jira_filter/__init__.py
b_jira_filter/commands/__init__.py
b_jira_filter/commands/common_main.py
b_jira_filter/commands/jira/__init__.py
b_jira_filter/commands/jira/main.py
b_jira_filter/commands/jira/sprints/__init__.py
b_jira_filter/commands/jira/sprints/main.py
b_jira_filter/commands/jira/sprints/storypoints.py
b_jira_filter/getters/__init__.py
b_jira_filter/getters/boards.py
b_jira_filter/getters/sprint_report.py
b_jira_filter/getters/sprints.py
b_jira_filter/getters/story_points_field.py
b_jira_filter/objects/__init__.py
b_jira_filter/objects/assignee.py
b_jira_filter/objects/credentials.py
b_jira_filter/objects/sprint_assignees.py
b_jira_filter/objects/sprint_issue.py
b_jira_filter/objects/sprint_story_points.py
b_jira_filter-0.0.4.dist-info/METADATA
b_jira_filter-0.0.4.dist-info/WHEEL
b_jira_filter-0.0.4.dist-info/entry_points.txt
b_jira_filter-0.0.4.dist-info/top_level.txt
b_jira_filter-0.0.4.dist-info/RECORD
