Metadata-Version: 2.1
Name: b-jira-filter
Version: 0.0.4
Summary: Script library to interact with JIRA API.
Home-page: UNKNOWN
Author: Laimonas Sutkus
Author-email: laimonas.sutkus@biomapas.com
License: Apache License 2.0
Keywords: JIRA
Platform: UNKNOWN
Classifier: Programming Language :: Python :: 3.8
Classifier: Operating System :: OS Independent
Requires-Dist: jira (<3.0.0,>=2.0.0)
